scenarios/__init__.py
scenarios-0.0.2.dist-info/LICENSE
scenarios-0.0.2.dist-info/METADATA
scenarios-0.0.2.dist-info/WHEEL
scenarios-0.0.2.dist-info/top_level.txt
scenarios-0.0.2.dist-info/RECORD
